odoo/addons/stock_picking_auto_create_package/README.rst
odoo/addons/stock_picking_auto_create_package/__init__.py
odoo/addons/stock_picking_auto_create_package/__manifest__.py
odoo/addons/stock_picking_auto_create_package/i18n/stock_picking_auto_create_package.pot
odoo/addons/stock_picking_auto_create_package/models/__init__.py
odoo/addons/stock_picking_auto_create_package/models/stock_picking.py
odoo/addons/stock_picking_auto_create_package/models/stock_picking_type.py
odoo/addons/stock_picking_auto_create_package/readme/CONFIGURE.rst
odoo/addons/stock_picking_auto_create_package/readme/CONTRIBUTORS.rst
odoo/addons/stock_picking_auto_create_package/readme/DESCRIPTION.rst
odoo/addons/stock_picking_auto_create_package/static/description/icon.png
odoo/addons/stock_picking_auto_create_package/static/description/index.html
odoo/addons/stock_picking_auto_create_package/tests/__init__.py
odoo/addons/stock_picking_auto_create_package/tests/test_automatic_package.py
odoo/addons/stock_picking_auto_create_package/views/stock_picking_type.xml
odoo14_addon_stock_picking_auto_create_package-14.0.1.1.1.dist-info/METADATA
odoo14_addon_stock_picking_auto_create_package-14.0.1.1.1.dist-info/WHEEL
odoo14_addon_stock_picking_auto_create_package-14.0.1.1.1.dist-info/top_level.txt
odoo14_addon_stock_picking_auto_create_package-14.0.1.1.1.dist-info/RECORD
