Metadata-Version: 2.1
Name: odoo14-addon-stock_picking_auto_create_package
Version: 14.0.1.1.1
Summary: Put all move lines in packs on validation.
Home-page: https://github.com/OCA/stock-logistics-workflow
Author: BCIM,MT Software,Raumschmiede,Odoo Community Association (OCA)
Author-email: support@odoo-community.org
License: AGPL-3
Classifier: Programming Language :: Python
Classifier: Framework :: Odoo
Classifier: Framework :: Odoo :: 14.0
Classifier: License :: OSI Approved :: GNU Affero General Public License v3
Requires-Python: >=3.6
Requires-Dist: odoo <14.1dev,>=14.0a
